alphaquantum/__init__.py
alphaquantum/alphaquantum.py
alphaquantum-0.1.0.dist-info/LICENSE
alphaquantum-0.1.0.dist-info/METADATA
alphaquantum-0.1.0.dist-info/WHEEL
alphaquantum-0.1.0.dist-info/RECORD
