Metadata-Version: 2.1
Name: alphaquantum
Version: 0.1.0
Summary: Open source algorithmic trading paltform
License: Apache Software License 2.0
Author: antobzzll
Author-email: 106315448+antobzzll@users.noreply.github.com
Requires-Python: >=3.11,<4.0
Classifier: License :: Other/Proprietary License
Classifier: Programming Language :: Python :: 3
Classifier: Programming Language :: Python :: 3.11
Classifier: Programming Language :: Python :: 3.12
